<?xml version="1.0" encoding="UTF-8"?>
<objects serializationModel="Studio.01.10.00">
    <object class="AudioFile" id="{2206869c-cadf-4662-9a7d-7e8c11de7d73}">
        <property name="assetPath">
            <value>FootstepsSnow_BW.59660.wav</value>
        </property>
        <property name="frequencyInKHz">
            <value>96</value>
        </property>
        <property name="channelCount">
            <value>2</value>
        </property>
        <property name="length">
            <value>0.42133333333333334</value>
        </property>
        <relationship name="masterAssetFolder">
            <destination>{83b02e40-5e69-430d-beb8-e8d2379b1716}</destination>
        </relationship>
    </object>
</objects>
